week4/delay/delay_inv.v
// module that models delay
module delay_inv(out, in, ctrl);
  input in, ctrl;
  output out;
  
  notif1 n1(out,in,ctrl);
endmodule

week4/delay/delay_inv_tb.v
`timescale 1ns/1ns
module delay_tb();
  reg in;
  reg ctrl;
  wire out;
  
  delay_inv #(20,40,60) d1(out, in, ctrl);
  
  // Initialize
  initial begin
    in = 0;
	ctrl = 0;
    #900 $finish;
  end

  always begin
	#100 in = ~ in;
  end
  
  always begin
    #200 ctrl = ~ ctrl;
  end
	
  //always
	//#200 ctrl = ~ctrl; // change control
	
  
  initial begin // GTKWAVE
    $dumpfile("output.vcd");
    $dumpvars(0);
  end	
endmodule

/*
`timescale 1ns/1ns
module delay_tb();
  reg in;
  ret ctrl;
  wire out_2130;
  
  delay_inv #(40,60,80) delay(out_2130, in, ctrl);
  
  // Initialize
  initial begin
    in = 0; ctrl = 1;
    #1200 $finish;
  end

  always
	#100 in = ~in; // change input
	
  //always
	//#200 ctrl = ~ctrl; // change control
	
  
  initial begin // GTKWAVE
    $dumpfile("output.vcd");
    $dumpvars(0);
  end	


endmodule
*/

week4/delay/output.vcd
$date
	Sun Apr 03 08:15:03 2022
$end
$version
	Icarus Verilog
$end
$timescale
	1ns
$end
$scope module delay_tb $end
$var wire 1 ! out $end
$var reg 1 " ctrl $end
$var reg 1 # in $end
$upscope $end
$enddefinitions $end
#0
$dumpvars
0#
0"
x!
$end
#5
1#
#8
z!
#10
1"
#15
0#
#19
1!
#20
0"
#25
1#
#28
z!
#30
1"
#35
0#
#39
1!
#40
0"
#45
1#
#48
z!
#50
1"
#55
0#
#59
1!
#60
0"
#65
1#
#68
z!
#70
1"
#75
0#
#79
1!
#80
0"
#85
1#
#88
z!
#90
1"
#95
0#
#99
1!
#100
0"
