week11/convert/part2/ascii_converter.v
`timescale 1ns/10ps

module ascii_converter(clk,rst,data,ascii,complete);
  // Port Declaration
  input clk, rst, data;
  output reg complete;
  output reg [6:0] ascii;
  
  integer i;
  reg [6:0] tmp;
  
  // Merge
  always @(posedge clk, negedge rst) begin
	// 리셋 : 레지스터 값 초기화 
	if (~rst) begin 
	  i=6; tmp=7'b0; 
	end// 저장 : 들어오는 1-bit data를 tmp에 저장해둔다
	else begin  
	  tmp[i] = data;	
	  i = i-1;
	  
	  // 출력 : 7개의 데이터가 들어올 때마다 저장되어 있던 7-bit 출력함과 동시에
	  //       complete 제어 신호 ON, 레지스터 값 초기화
	  if (i==-1) begin
	    i = 6;
	    complete = 1'b1;
	    ascii = tmp;
	    tmp = 7'b0;
	  end
	  else
	    complete = 1'b0;
	end
	
  end
endmodule

proj2/part1/ascii_converter_tb.v
`timescale 1ns/1ns
module ascii_converter_tb();
  /* Port Declaration */
  reg clk,rst;
  reg [83:0] data;
  
  wire complete;
  wire [6:0] ascii;
  integer i;
  ascii_converter m1(clk,rst,data[i],ascii,complete);
 
  /* Initialize */
  initial begin 
    $dumpfile("output.vcd");
	$dumpvars(0);
  end
  
  initial begin 
    data = 84'b100100011001011101100110110011011111011111101011111011111110010110110011001000101011;
	clk = 0; rst = 0; i = 83;
    
	#1 rst = 1;
	#200 $finish;
  end
  
  /* Iterate */
  always
    #0.5 clk = ~clk;
 
  always @(posedge clk, negedge rst) begin
    if (rst) begin // not reset
	  #1 i = i-1;
	end
  end
  
  always @(posedge complete)
    $write("%s",ascii);
endmodule

week11/output.vcd
$date
	Thu May 26 12:38:20 2022
$end
$version
	Icarus Verilog
$end
$timescale
	10ps
$end
$scope module ascii_converter_tb $end
$var wire 1 ! complete $end
$var wire 7 " ascii [6:0] $end
$var reg 1 # clk $end
$var reg 84 $ data [83:0] $end
$var reg 1 % rst $end
$var integer 32 & i [31:0] $end
$scope module m1 $end
$var wire 1 # clk $end
$var wire 1 ' data $end
$var wire 1 % rst $end
$var reg 7 ( ascii [6:0] $end
$var reg 1 ! complete $end
$var reg 7 ) tmp [6:0] $end
$var integer 32 * i [31:0] $end
$upscope $end
$upscope $end
$enddefinitions $end
#0
$dumpvars
b110 *
b0 )
bx (
1'
b1010011 &
0%
b100100011001011101100110110011011111011111101011111011111110010110110011001000101011 $
0#
bx "
0!
$end
#100
b101 *
b1000000 )
1#
1%
#200
0'
b1010010 &
0#
#300
b100 *
1#
#400
b1010001 &
0#
#500
b11 *
1#
#600
1'
b1010000 &
0#
#700
b10 *
b1001000 )
1#
#800
0'
b1001111 &
0#
#900
b1 *
1#
#1000
b1001110 &
0#
#1100
b0 *
1#
#1200
b1001101 &
0#
#1300
b0 )
b1001000 "
b1001000 (
1!
b110 *
1#
#1400
1'
b1001100 &
0#
#1500
b101 *
b1000000 )
0!
1#
#1600
b1001011 &
0#
#1700
b100 *
b1100000 )
1#
#1800
0'
b1001010 &
0#
#1900
b11 *
1#
#2000
b1001001 &
0#
#2100
b10 *
1#
#2200
1'
b1001000 &
0#
#2300
b1 *
b1100100 )
1#
#2400
0'
b1000111 &
0#
#2500
b0 *
1#
#2600
1'
b1000110 &
0#
#2700
b1100101 "
b1100101 (
1!
b110 *
b0 )
1#
#2800
b1000101 &
0#
#2900
b101 *
b1000000 )
0!
1#
#3000
b1000100 &
0#
#3100
b100 *
b1100000 )
1#
#3200
0'
b1000011 &
0#
#3300
b11 *
1#
#3400
1'
b1000010 &
0#
#3500
b10 *
b1101000 )
1#
#3600
b1000001 &
0#
#3700
b1 *
b1101100 )
1#
#3800
0'
b1000000 &
0#
#3900
b0 *
1#
#4000
b111111 &
0#
#4100
b0 )
b1101100 "
b1101100 (
1!
b110 *
1#
#4200
1'
b111110 &
0#
#4300
b101 *
b1000000 )
0!
1#
#4400
b111101 &
0#
#4500
b100 *
b1100000 )
1#
#4600
0'
b111100 &
0#
#4700
b11 *
1#
#4800
1'
b111011 &
0#
#4900
b10 *
b1101000 )
1#
#5000
b111010 &
0#
#5100
b1 *
b1101100 )
1#
#5200
0'
b111001 &
0#
#5300
b0 *
1#
#5400
b111000 &
0#
#5500
b0 )
1!
b110 *
1#
#5600
1'
b110111 &
0#
#5700
b101 *
b1000000 )
0!
1#
#5800
b110110 &
0#
#5900
b100 *
b1100000 )
1#
#6000
0'
b110101 &
0#
#6100
b11 *
1#
#6200
1'
b110100 &
0#
#6300
b10 *
b1101000 )
1#
#6400
b110011 &
0#
#6500
b1 *
b1101100 )
1#
#6600
b110010 &
0#
#6700
b0 *
b1101110 )
1#
#6800
b110001 &
0#
#6900
b1101111 "
b1101111 (
1!
b110 *
b0 )
1#
#7000
b110000 &
0#
#7100
b101 *
b1000000 )
0!
1#
#7200
0'
b101111 &
0#
#7300
b100 *
1#
#7400
1'
b101110 &
0#
#7500
b11 *
b1010000 )
1#
#7600
b101101 &
0#
#7700
b10 *
b1011000 )
1#
#7800
b101100 &
0#
#7900
b1 *
b1011100 )
1#
#8000
b101011 &
0#
#8100
b0 *
b1011110 )
1#
#8200
b101010 &
0#
#8300
b1011111 "
b1011111 (
1!
b110 *
b0 )
1#
#8400
b101001 &
0#
#8500
b101 *
b1000000 )
0!
1#
#8600
0'
b101000 &
0#
#8700
b100 *
1#
#8800
1'
b100111 &
0#
#8900
b11 *
b1010000 )
1#
#9000
0'
b100110 &
0#
#9100
b10 *
1#
#9200
1'
b100101 &
0#
#9300
b1 *
b1010100 )
1#
#9400
b100100 &
0#
#9500
b0 *
b1010110 )
1#
#9600
b100011 &
0#
#9700
b1010111 "
b1010111 (
1!
b110 *
b0 )
1#
#9800
b100010 &
0#
#9900
b101 *
b1000000 )
0!
1#
#10000
b100001 &
0#
#10100
b100 *
b1100000 )
1#
#10200
0'
b100000 &
0#
#10300
b11 *
1#
#10400
1'
b11111 &
0#
#10500
b10 *
b1101000 )
1#
#10600
b11110 &
0#
#10700
b1 *
b1101100 )
1#
#10800
b11101 &
0#
#10900
b0 *
b1101110 )
1#
#11000
b11100 &
0#
#11100
b1101111 "
b1101111 (
1!
b110 *
b0 )
1#
#11200
b11011 &
0#
#11300
b101 *
b1000000 )
0!
1#
#11400
b11010 &
0#
#11500
b100 *
b1100000 )
1#
#11600
b11001 &
0#
#11700
b11 *
b1110000 )
1#
#11800
0'
b11000 &
0#
#11900
b10 *
1#
#12000
b10111 &
0#
#12100
b1 *
1#
#12200
1'
b10110 &
0#
#12300
b0 *
b1110010 )
1#
#12400
0'
b10101 &
0#
#12500
b0 )
b1110010 "
b1110010 (
1!
b110 *
1#
#12600
1'
b10100 &
0#
#12700
b101 *
b1000000 )
0!
1#
#12800
b10011 &
0#
#12900
b100 *
b1100000 )
1#
#13000
0'
b10010 &
0#
#13100
b11 *
1#
#13200
1'
b10001 &
0#
#13300
b10 *
b1101000 )
1#
#13400
b10000 &
0#
#13500
b1 *
b1101100 )
1#
#13600
0'
b1111 &
0#
#13700
b0 *
1#
#13800
b1110 &
0#
#13900
b0 )
b1101100 "
b1101100 (
1!
b110 *
1#
#14000
1'
b1101 &
0#
#14100
b101 *
b1000000 )
0!
1#
#14200
b1100 &
0#
#14300
b100 *
b1100000 )
1#
#14400
0'
b1011 &
0#
#14500
b11 *
1#
#14600
b1010 &
0#
#14700
b10 *
1#
#14800
1'
b1001 &
0#
#14900
b1 *
b1100100 )
1#
#15000
0'
b1000 &
0#
#15100
b0 *
1#
#15200
b111 &
0#
#15300
b0 )
b1100100 "
b1100100 (
1!
b110 *
1#
#15400
b110 &
0#
#15500
b101 *
0!
1#
#15600
1'
b101 &
0#
#15700
b100 *
b100000 )
1#
#15800
0'
b100 &
0#
#15900
b11 *
1#
#16000
1'
b11 &
0#
#16100
b10 *
b101000 )
1#
#16200
0'
b10 &
0#
#16300
b1 *
1#
#16400
1'
b1 &
0#
#16500
b0 *
b101010 )
1#
#16600
b0 &
0#
#16700
b101011 "
b101011 (
1!
b110 *
b0 )
1#
#16800
x'
b11111111111111111111111111111111 &
0#
#16900
b101 *
bx000000 )
0!
1#
#17000
b11111111111111111111111111111110 &
0#
#17100
b100 *
bx00000 )
1#
#17200
b11111111111111111111111111111101 &
0#
#17300
b11 *
bx0000 )
1#
#17400
b11111111111111111111111111111100 &
0#
#17500
b10 *
bx000 )
1#
#17600
b11111111111111111111111111111011 &
0#
#17700
b1 *
bx00 )
1#
#17800
b11111111111111111111111111111010 &
0#
#17900
b0 *
bx0 )
1#
#18000
b11111111111111111111111111111001 &
0#
#18100
bx "
bx (
1!
b110 *
b0 )
1#
#18200
b11111111111111111111111111111000 &
0#
#18300
b101 *
bx000000 )
0!
1#
#18400
b11111111111111111111111111110111 &
0#
#18500
b100 *
bx00000 )
1#
#18600
b11111111111111111111111111110110 &
0#
#18700
b11 *
bx0000 )
1#
#18800
b11111111111111111111111111110101 &
0#
#18900
b10 *
bx000 )
1#
#19000
b11111111111111111111111111110100 &
0#
#19100
b1 *
bx00 )
1#
#19200
b11111111111111111111111111110011 &
0#
#19300
b0 *
bx0 )
1#
#19400
b11111111111111111111111111110010 &
0#
#19500
1!
b110 *
b0 )
1#
#19600
b11111111111111111111111111110001 &
0#
#19700
b101 *
bx000000 )
0!
1#
#19800
b11111111111111111111111111110000 &
0#
#19900
b100 *
bx00000 )
1#
#20000
b11111111111111111111111111101111 &
0#
#20100
b11 *
bx0000 )
1#
